jmobile_location_mcp_server/__init__.py
jmobile_location_mcp_server/__main__.py
jmobile_location_mcp_server/server.py
jmobile_location_mcp_server-0.1.1.dist-info/METADATA
jmobile_location_mcp_server-0.1.1.dist-info/WHEEL
jmobile_location_mcp_server-0.1.1.dist-info/entry_points.txt
jmobile_location_mcp_server-0.1.1.dist-info/RECORD
