Metadata-Version: 2.4
Name: jmobile-location-mcp-server
Version: 0.1.1
Summary: 一个提供手机号码（段）所属归属地查询功能的模型上下文协议（Model Context Protocol）服务器。该服务器使大型语言模型（LLMs）能够获取手机号码段归属地信息，如：省份、城市、运营商。
Author-email: juhemcp <dev@juheapi.com>
Requires-Python: >=3.10
Requires-Dist: mcp[cli]>=1.4.1
